<?xml version='1.0' encoding='utf-8'?>
<lom xmlns="http://ltsc.ieee.org/xsd/LOM">
	<general>
		<identifier>
			<entry>https://example.com/objectMetadata/20</entry>
		</identifier>
		<title>
			<string language="en-US">Learning Object 20</string>
		</title>
		<language>en-US</language>
		<description>
			<string language="en-US">The principles and practices used in the architecture and design of outdoor areas.</string>
		</description>
		<keyword>
			<string language="en-US">Learning</string>
			<string language="en-US">Object</string>
			<string language="en-US">20</string>
		</keyword>
	</general>
	<educational>
		<interactivityType>
			<source>LOMv1.0</source>
			<value>active</value>
		</interactivityType>
		<learningResourceType>
			<source>LOMv1.0</source>
			<value>table</value>
		</learningResourceType>
		<interactivityLevel>
			<source>LOMv1.0</source>
			<value>very low</value>
		</interactivityLevel>
		<semanticDensity>
			<source>LOMv1.0</source>
			<value>very low</value>
		</semanticDensity>
		<difficulty>
			<source>LOMv1.0</source>
			<value>very easy</value>
		</difficulty>
		<typicalLearningTime>
			<duration>PT27M44S</duration>
		</typicalLearningTime>
	</educational>
	<classification>
		<purpose>
			<source>LOMv1.0</source>
			<value>competency</value>
		</purpose>
		<taxonPath>
			<source>
				<string language="en-US">ESCO</string>
			</source>
			<taxon>
				<id>http://data.europa.eu/esco/skill/4c598891-db23-4b7c-9b39-233ba8eaf848</id>
				<entry>
					<string language="en-US">landscape architecture</string>
				</entry>
			</taxon>
		</taxonPath>
	</classification>
</lom>